gogotable/__init__.py
gogotable/gogotable.py
gogotable-0.1.3.dist-info/LICENSE
gogotable-0.1.3.dist-info/METADATA
gogotable-0.1.3.dist-info/WHEEL
gogotable-0.1.3.dist-info/RECORD
