Metadata-Version: 2.1
Name: gogotable
Version: 0.1.3
Summary: Convert structured data to a table
License: Unlicense
Author: Luís Miranda
Author-email: luistm@gmail.com
Requires-Python: >=3.9,<4.0
Classifier: License :: OSI Approved
Classifier: Programming Language :: Python :: 3
Classifier: Programming Language :: Python :: 3.9
Classifier: Programming Language :: Python :: 3.10
Classifier: Programming Language :: Python :: 3.11
Classifier: Programming Language :: Python :: 3.12
